apiaudio/__init__.py
apiaudio/api_request.py
apiaudio/helper_classes.py
apiaudio/logging.py
apiaudio/api_resources/__init__.py
apiaudio/api_resources/birdcache.py
apiaudio/api_resources/connector.py
apiaudio/api_resources/dictionary.py
apiaudio/api_resources/mastering.py
apiaudio/api_resources/media.py
apiaudio/api_resources/orchestrator.py
apiaudio/api_resources/organization.py
apiaudio/api_resources/script.py
apiaudio/api_resources/sound.py
apiaudio/api_resources/speech.py
apiaudio/api_resources/syncTTS.py
apiaudio/api_resources/voice.py
apiaudio/api_resources/webhooks.py
tests/__init__.py
tests/test_config.py
apiaudio-0.17.1.dist-info/LICENSE
apiaudio-0.17.1.dist-info/METADATA
apiaudio-0.17.1.dist-info/WHEEL
apiaudio-0.17.1.dist-info/top_level.txt
apiaudio-0.17.1.dist-info/RECORD
