Metadata-Version: 2.1
Name: apiaudio
Version: 0.17.1
Summary: Python SDK for api.audio API
Home-page: https://github.com/aflorithmic/apiaudio-python
Author: Aflorithmic
Author-email: linda@aflorithmic.ai
Classifier: Programming Language :: Python :: 3
Classifier: License :: OSI Approved :: MIT License
Classifier: Operating System :: OS Independent
Requires-Python: >=3.6
License-File: LICENSE
Requires-Dist: requests >=2.20 ; python_version >= "3.0"
